logging_middleware/__init__.py
logging_middleware/middleware.py
fastapi_logging_middleware-0.1.2.dist-info/METADATA
fastapi_logging_middleware-0.1.2.dist-info/WHEEL
fastapi_logging_middleware-0.1.2.dist-info/licenses/LICENSE
fastapi_logging_middleware-0.1.2.dist-info/RECORD
