Metadata-Version: 2.4
Name: fastapi-logging-middleware
Version: 0.1.2
Summary: Beautiful, colorful HTTP request logs in Go-style format for FastAPI applications
Project-URL: Homepage, https://github.com/AnthonyHol/fastapi-logging-middleware
Project-URL: Repository, https://github.com/AnthonyHol/fastapi-logging-middleware
Project-URL: Issues, https://github.com/AnthonyHol/fastapi-logging-middleware/issues
Author-email: AnthonyHol <kholkin.anthony@gmail.com>
License: MIT
License-File: LICENSE
Keywords: colorful,fastapi,go-style,logging,middleware
Classifier: Development Status :: 4 - Beta
Classifier: Framework :: FastAPI
Classifier: Intended Audience :: Developers
Classifier: License :: OSI Approved :: MIT License
Classifier: Programming Language :: Python :: 3
Classifier: Programming Language :: Python :: 3.11
Classifier: Programming Language :: Python :: 3.12
Classifier: Topic :: Internet :: WWW/HTTP :: HTTP Servers
Classifier: Topic :: Software Development :: Libraries :: Python Modules
Classifier: Topic :: System :: Logging
Requires-Python: >=3.11
Requires-Dist: colorama>=0.4.6
Requires-Dist: fastapi>=0.110.0
Requires-Dist: starlette>=0.37.0
